{
  "run_id": "bollinger_atr_TIAUSDC_1d_20260222_161530_3aa1d35f",
  "timestamp": "2026-02-22T16:15:30.560940",
  "strategy": "BollingerATR",
  "symbol": "TIAUSDC",
  "timeframe": "1d",
  "params": {
    "initial_capital": 10000,
    "fees_bps": 10,
    "slippage_bps": 5,
    "bb_period": 14,
    "bb_std": 1.3,
    "atr_period": 7,
    "atr_percentile": 72,
    "entry_z": 1.9,
    "k_sl": 2.95,
    "leverage": 1.0
  },
  "metrics": {
    "total_pnl": 6553.909399388769,
    "total_return_pct": 65.53909399388769,
    "sharpe_ratio": 2.0244515261253833,
    "max_drawdown_pct": -3.436076996961055,
    "total_trades": 23,
    "win_rate_pct": 69.56521739130434,
    "profit_factor": 11.11571007711019,
    "data_coverage_pct": 100.0
  },
  "n_bars": 808,
  "n_trades": 23,
  "period_start": "2023-11-16 00:00:00+00:00",
  "period_end": "2026-01-31 00:00:00+00:00",
  "duration_sec": 0.1545405000069877
}