{
  "session_id": "20260212_153211_strat_gie_de_momentum_sur_btcusdc_30m_in",
  "objective": "Strat\u00e9gie de Momentum sur BTCUSDC 30m. Indicateurs : MACD + STOCHASTIC + ATR. Position quand le momentum (MACD) acc\u00e9l\u00e8re et STOCHASTIC est align\u00e9. Sortie quand le momentum (MACD) s'\u00e9puise ou diverge du prix. Long uniquement. Stop-loss = 1.5x ATR, take-profit = 3.0x ATR (RR 2.0:1).",
  "status": "failed",
  "best_sharpe": -20.0,
  "total_iterations": 10,
  "available_indicators": [
    "bollinger",
    "atr",
    "rsi",
    "ema",
    "sma",
    "macd",
    "adx",
    "stochastic",
    "vwap",
    "donchian",
    "cci",
    "keltner",
    "mfi",
    "williams_r",
    "momentum",
    "obv",
    "roc",
    "aroon",
    "supertrend",
    "fear_greed",
    "fibonacci_levels",
    "ichimoku",
    "onchain_smoothing",
    "pi_cycle",
    "pivot_points",
    "psar",
    "standard_deviation",
    "volume_oscillator",
    "vortex",
    "amplitude_hunter",
    "stoch_rsi"
  ],
  "iterations": [
    {
      "iteration": 1,
      "hypothesis": "This strategy capitalizes on the convergence of momentum acceleration (MACD) with stochastic alignment to identify high-probability long entries in BTCUSDC. MACD's signal line crossing above its histogram indicates acceleration in bullish momentum, while stochastic confirmation ensures price is not overextended. The ATR-based risk management ensures position sizing and stop-loss/take-profit levels scale with market volatility, providing consistent risk-reward ratios and robust performance across varying market conditions.",
      "change_type": "accept",
      "diagnostic_category": "ruined",
      "error": null,
      "decision": "continue",
      "sharpe": 0.8080259558588733,
      "return_pct": -2759.74168394525,
      "trades": 2559,
      "score_card": {
        "profitability": {
          "grade": "F",
          "detail": "Return -2759.7%, PF 0.72, Expectancy 0.00"
        },
        "risk": {
          "grade": "F",
          "detail": "MaxDD 100.0%, Vol 0.0%"
        },
        "efficiency": {
          "grade": "C",
          "detail": "Sharpe 0.808, Sortino 0.000, Calmar 0.000"
        },
        "signal_quality": {
          "grade": "D",
          "detail": "WR 29.2%, Trades 2559, AvgW/L 0.00/0.00"
        }
      },
      "phase_feedback": {
        "proposal": {
          "phase": "proposal",
          "initial_kind": "json",
          "realign_attempts": 0,
          "realign_success": false,
          "issues": [],
          "final_kind": "json",
          "final_valid": true
        },
        "code": {
          "phase": "code",
          "initial_kind": "python",
          "realign_attempts": 0,
          "realign_success": false,
          "final_kind": "python",
          "final_valid": true,
          "validation_error": "Usage invalide: `macd['macd_line']` pour indicateur dict 'macd'. Sous-cl\u00e9s valides: histogram, macd, signal.",
          "validation_error_retry": "Usage invalide: indicators['stochastic']['k'] \u2014 sous-cl\u00e9 inconnue. Sous-cl\u00e9s valides: stoch_d, stoch_k.",
          "fallback_deterministic_used": true,
          "source": "deterministic_fallback"
        },
        "decision": {
          "stop_overridden": true
        }
      }
    },
    {
      "iteration": 2,
      "hypothesis": "The previous strategy failed because it relied on RSI and Bollinger Bands which are prone to whipsaws and false signals in volatile markets like BTCUSDC. This new approach focuses purely on MACD momentum acceleration combined with STOCHASTIC alignment to identify strong trend continuation signals. MACD acceleration indicates momentum is building, while STOCHASTIC alignment confirms price is moving in the same direction as the trend. The combination reduces false signals significantly compared to RSI-based filters. ATR-based risk management ensures proper position sizing and consistent risk-reward ratios.",
      "change_type": "logic",
      "diagnostic_category": "ruined",
      "error": null,
      "decision": "continue",
      "sharpe": 0.8080259558588733,
      "return_pct": -2759.74168394525,
      "trades": 2559,
      "score_card": {
        "profitability": {
          "grade": "F",
          "detail": "Return -2759.7%, PF 0.72, Expectancy 0.00"
        },
        "risk": {
          "grade": "F",
          "detail": "MaxDD 100.0%, Vol 0.0%"
        },
        "efficiency": {
          "grade": "C",
          "detail": "Sharpe 0.808, Sortino 0.000, Calmar 0.000"
        },
        "signal_quality": {
          "grade": "D",
          "detail": "WR 29.2%, Trades 2559, AvgW/L 0.00/0.00"
        }
      },
      "phase_feedback": {
        "proposal": {
          "phase": "proposal",
          "initial_kind": "json",
          "realign_attempts": 0,
          "realign_success": false,
          "issues": [],
          "final_kind": "json",
          "final_valid": true
        },
        "code": {
          "phase": "code",
          "initial_kind": "python",
          "realign_attempts": 0,
          "realign_success": false,
          "final_kind": "python",
          "final_valid": true,
          "validation_error": "Usage invalide: `stochastic['k']` pour indicateur dict 'stochastic'. Sous-cl\u00e9s valides: stoch_d, stoch_k.",
          "validation_error_retry": "Usage invalide: indicators['stochastic']['k'] \u2014 sous-cl\u00e9 inconnue. Sous-cl\u00e9s valides: stoch_d, stoch_k.",
          "fallback_deterministic_used": true,
          "source": "deterministic_fallback"
        },
        "decision": {
          "stop_overridden": true
        }
      }
    },
    {
      "iteration": 3,
      "hypothesis": "The previous strategy failed because it relied on RSI and Bollinger Bands which are prone to whipsaws in trending markets. This new approach uses MACD for momentum acceleration detection and Stochastic for momentum alignment confirmation, both in conjunction with ATR for dynamic risk management. MACD's signal line crossing above the histogram indicates acceleration, while Stochastic's alignment with price confirms momentum strength. The combination reduces false signals and improves trade quality, with ATR-based stops ensuring proper risk-reward ratios.",
      "change_type": "logic",
      "diagnostic_category": "ruined",
      "error": null,
      "decision": "continue",
      "sharpe": 0.8080259558588733,
      "return_pct": -2759.74168394525,
      "trades": 2559,
      "score_card": {
        "profitability": {
          "grade": "F",
          "detail": "Return -2759.7%, PF 0.72, Expectancy 0.00"
        },
        "risk": {
          "grade": "F",
          "detail": "MaxDD 100.0%, Vol 0.0%"
        },
        "efficiency": {
          "grade": "C",
          "detail": "Sharpe 0.808, Sortino 0.000, Calmar 0.000"
        },
        "signal_quality": {
          "grade": "D",
          "detail": "WR 29.2%, Trades 2559, AvgW/L 0.00/0.00"
        }
      },
      "phase_feedback": {
        "proposal": {
          "phase": "proposal",
          "initial_kind": "json",
          "realign_attempts": 0,
          "realign_success": false,
          "issues": [],
          "final_kind": "json",
          "final_valid": true
        },
        "code": {
          "phase": "code",
          "initial_kind": "python",
          "realign_attempts": 0,
          "realign_success": false,
          "final_kind": "python",
          "final_valid": true,
          "validation_error": "Usage invalide: `stochastic['k']` pour indicateur dict 'stochastic'. Sous-cl\u00e9s valides: stoch_d, stoch_k.",
          "validation_error_retry": "Usage invalide: indicators['stochastic']['k'] \u2014 sous-cl\u00e9 inconnue. Sous-cl\u00e9s valides: stoch_d, stoch_k.",
          "fallback_deterministic_used": true,
          "source": "deterministic_fallback"
        },
        "decision": {
          "stop_overridden": true
        }
      }
    },
    {
      "iteration": 4,
      "hypothesis": "The previous strategy failed because it relied on RSI and Bollinger Bands which are prone to whipsaws and false signals in volatile BTC markets. This new approach focuses purely on MACD momentum acceleration combined with STOCHASTIC alignment to identify strong trend continuations. By using ATR for dynamic stop-loss and take-profit levels, we ensure proper risk management that adapts to market volatility. The combination of MACD and STOCHASTIC provides high-quality entry signals while filtering out weak or false breakouts.",
      "change_type": "logic",
      "diagnostic_category": "ruined",
      "error": null,
      "decision": "continue",
      "sharpe": 0.8080259558588733,
      "return_pct": -2759.74168394525,
      "trades": 2559,
      "score_card": {
        "profitability": {
          "grade": "F",
          "detail": "Return -2759.7%, PF 0.72, Expectancy 0.00"
        },
        "risk": {
          "grade": "F",
          "detail": "MaxDD 100.0%, Vol 0.0%"
        },
        "efficiency": {
          "grade": "C",
          "detail": "Sharpe 0.808, Sortino 0.000, Calmar 0.000"
        },
        "signal_quality": {
          "grade": "D",
          "detail": "WR 29.2%, Trades 2559, AvgW/L 0.00/0.00"
        }
      },
      "phase_feedback": {
        "proposal": {
          "phase": "proposal",
          "initial_kind": "json",
          "realign_attempts": 0,
          "realign_success": false,
          "issues": [],
          "final_kind": "json",
          "final_valid": true
        },
        "code": {
          "phase": "code",
          "initial_kind": "python",
          "realign_attempts": 0,
          "realign_success": false,
          "final_kind": "python",
          "final_valid": true,
          "validation_error": "Usage invalide: `stochastic['k']` pour indicateur dict 'stochastic'. Sous-cl\u00e9s valides: stoch_d, stoch_k.",
          "validation_error_retry": "Usage invalide: indicators['stochastic']['k'] \u2014 sous-cl\u00e9 inconnue. Sous-cl\u00e9s valides: stoch_d, stoch_k.",
          "fallback_deterministic_used": true,
          "source": "deterministic_fallback"
        },
        "decision": {
          "stop_overridden": true
        }
      }
    },
    {
      "iteration": 5,
      "hypothesis": "The previous strategy failed because it relied on RSI and Bollinger Bands for entry, which are lagging indicators that often generate false signals in trending markets like BTCUSDC. This revised approach uses MACD for momentum confirmation, STOCHASTIC for trend alignment, and ATR for dynamic risk management. The combination filters for accelerating momentum (MACD histogram increasing) and aligned stochastic (stochastic crossing above 50), ensuring entries are in strong trend direction. ATR-based stop-loss and take-profit provide dynamic risk controls with a 2:1 reward-to-risk ratio.",
      "change_type": "logic",
      "diagnostic_category": "ruined",
      "error": null,
      "decision": "continue",
      "sharpe": 0.8080259558588733,
      "return_pct": -2759.74168394525,
      "trades": 2559,
      "score_card": {
        "profitability": {
          "grade": "F",
          "detail": "Return -2759.7%, PF 0.72, Expectancy 0.00"
        },
        "risk": {
          "grade": "F",
          "detail": "MaxDD 100.0%, Vol 0.0%"
        },
        "efficiency": {
          "grade": "C",
          "detail": "Sharpe 0.808, Sortino 0.000, Calmar 0.000"
        },
        "signal_quality": {
          "grade": "D",
          "detail": "WR 29.2%, Trades 2559, AvgW/L 0.00/0.00"
        }
      },
      "phase_feedback": {
        "proposal": {
          "phase": "proposal",
          "initial_kind": "json",
          "realign_attempts": 0,
          "realign_success": false,
          "issues": [],
          "final_kind": "json",
          "final_valid": true
        },
        "code": {
          "phase": "code",
          "initial_kind": "python",
          "realign_attempts": 0,
          "realign_success": false,
          "final_kind": "python",
          "final_valid": true,
          "validation_error": "Usage invalide: `stochastic['k']` pour indicateur dict 'stochastic'. Sous-cl\u00e9s valides: stoch_d, stoch_k.",
          "validation_error_retry": "Usage invalide: indicators['stochastic']['k'] \u2014 sous-cl\u00e9 inconnue. Sous-cl\u00e9s valides: stoch_d, stoch_k.",
          "fallback_deterministic_used": true,
          "source": "deterministic_fallback"
        },
        "decision": {
          "stop_overridden": true
        }
      }
    },
    {
      "iteration": 6,
      "hypothesis": "The previous strategy failed because it relied on RSI and Bollinger Bands which are prone to whipsaws in trending markets. This new approach uses MACD for momentum confirmation, Stochastic for momentum alignment, and ATR for dynamic risk management. The key insight is that momentum acceleration (MACD histogram increasing) combined with stochastic alignment (stochastic in oversold/overbought regions) provides a more robust entry signal than traditional RSI crossovers. The ATR-based stop-loss and take-profit ensure proper risk-reward ratios while adapting to volatility changes.",
      "change_type": "logic",
      "diagnostic_category": "ruined",
      "error": null,
      "decision": "continue",
      "sharpe": 0.8080259558588733,
      "return_pct": -2759.74168394525,
      "trades": 2559,
      "score_card": {
        "profitability": {
          "grade": "F",
          "detail": "Return -2759.7%, PF 0.72, Expectancy 0.00"
        },
        "risk": {
          "grade": "F",
          "detail": "MaxDD 100.0%, Vol 0.0%"
        },
        "efficiency": {
          "grade": "C",
          "detail": "Sharpe 0.808, Sortino 0.000, Calmar 0.000"
        },
        "signal_quality": {
          "grade": "D",
          "detail": "WR 29.2%, Trades 2559, AvgW/L 0.00/0.00"
        }
      },
      "phase_feedback": {
        "proposal": {
          "phase": "proposal",
          "initial_kind": "json",
          "realign_attempts": 0,
          "realign_success": false,
          "issues": [],
          "final_kind": "json",
          "final_valid": true
        },
        "code": {
          "phase": "code",
          "initial_kind": "python",
          "realign_attempts": 0,
          "realign_success": false,
          "final_kind": "python",
          "final_valid": true,
          "validation_error": "Usage invalide: `stochastic['k']` pour indicateur dict 'stochastic'. Sous-cl\u00e9s valides: stoch_d, stoch_k.",
          "validation_error_retry": "Usage invalide: indicators['stochastic']['k'] \u2014 sous-cl\u00e9 inconnue. Sous-cl\u00e9s valides: stoch_d, stoch_k.",
          "fallback_deterministic_used": true,
          "source": "deterministic_fallback"
        },
        "decision": {
          "stop_overridden": true
        }
      }
    },
    {
      "iteration": 7,
      "hypothesis": "The strategy will improve by focusing strictly on momentum acceleration and alignment signals from MACD and Stochastic, eliminating overbought/oversold RSI filters that caused frequent false signals. By using only MACD crossover for entry and Stochastic confirmation for momentum alignment, we reduce whipsaw effects. The ATR-based risk management ensures proper position sizing and fixed RR 2.0:1 targets, while eliminating unnecessary Bollinger Bands that added noise.",
      "change_type": "logic",
      "diagnostic_category": "ruined",
      "error": null,
      "decision": "continue",
      "sharpe": 0.8080259558588733,
      "return_pct": -2759.74168394525,
      "trades": 2559,
      "score_card": {
        "profitability": {
          "grade": "F",
          "detail": "Return -2759.7%, PF 0.72, Expectancy 0.00"
        },
        "risk": {
          "grade": "F",
          "detail": "MaxDD 100.0%, Vol 0.0%"
        },
        "efficiency": {
          "grade": "C",
          "detail": "Sharpe 0.808, Sortino 0.000, Calmar 0.000"
        },
        "signal_quality": {
          "grade": "D",
          "detail": "WR 29.2%, Trades 2559, AvgW/L 0.00/0.00"
        }
      },
      "phase_feedback": {
        "proposal": {
          "phase": "proposal",
          "initial_kind": "json",
          "realign_attempts": 0,
          "realign_success": false,
          "issues": [],
          "final_kind": "json",
          "final_valid": true
        },
        "code": {
          "phase": "code",
          "initial_kind": "python",
          "realign_attempts": 0,
          "realign_success": false,
          "final_kind": "python",
          "final_valid": true,
          "validation_error": "Usage invalide: `stochastic['k']` pour indicateur dict 'stochastic'. Sous-cl\u00e9s valides: stoch_d, stoch_k.",
          "validation_error_retry": "Usage invalide: indicators['stochastic']['k'] \u2014 sous-cl\u00e9 inconnue. Sous-cl\u00e9s valides: stoch_d, stoch_k.",
          "fallback_deterministic_used": true,
          "source": "deterministic_fallback"
        },
        "decision": {
          "stop_overridden": true
        }
      }
    },
    {
      "iteration": 8,
      "hypothesis": "The current strategy fails because it uses RSI and Bollinger Bands as entry filters, which are prone to whipsaws and false signals in trending markets. By focusing exclusively on MACD momentum acceleration and STOCHASTIC alignment, we isolate true momentum shifts. The ATR-based risk management ensures proper position sizing and prevents catastrophic drawdowns. This combination filters out noise and captures genuine trend continuation opportunities, improving win rate and risk-reward profile.",
      "change_type": "logic",
      "diagnostic_category": "ruined",
      "error": null,
      "decision": "continue",
      "sharpe": 0.8080259558588733,
      "return_pct": -2759.74168394525,
      "trades": 2559,
      "score_card": {
        "profitability": {
          "grade": "F",
          "detail": "Return -2759.7%, PF 0.72, Expectancy 0.00"
        },
        "risk": {
          "grade": "F",
          "detail": "MaxDD 100.0%, Vol 0.0%"
        },
        "efficiency": {
          "grade": "C",
          "detail": "Sharpe 0.808, Sortino 0.000, Calmar 0.000"
        },
        "signal_quality": {
          "grade": "D",
          "detail": "WR 29.2%, Trades 2559, AvgW/L 0.00/0.00"
        }
      },
      "phase_feedback": {
        "proposal": {
          "phase": "proposal",
          "initial_kind": "json",
          "realign_attempts": 0,
          "realign_success": false,
          "issues": [],
          "final_kind": "json",
          "final_valid": true
        },
        "code": {
          "phase": "code",
          "initial_kind": "python",
          "realign_attempts": 0,
          "realign_success": false,
          "final_kind": "python",
          "final_valid": true,
          "validation_error": "Usage invalide: `stochastic['k']` pour indicateur dict 'stochastic'. Sous-cl\u00e9s valides: stoch_d, stoch_k.",
          "validation_error_retry": "Usage invalide: indicators['stochastic']['k'] \u2014 sous-cl\u00e9 inconnue. Sous-cl\u00e9s valides: stoch_d, stoch_k.",
          "fallback_deterministic_used": true,
          "source": "deterministic_fallback"
        },
        "decision": {
          "stop_overridden": true
        }
      }
    },
    {
      "iteration": 9,
      "hypothesis": "The previous strategy failed because it relied on RSI and Bollinger Bands for entry, which generated excessive false signals and led to ruinous drawdowns. This revised approach focuses purely on MACD momentum acceleration and STOCHASTIC alignment for entries, filtering out weak momentum signals. ATR-based stop-loss and take-profit ensure consistent risk-reward ratios with a 2:1 target. The combination of MACD and STOCHASTIC provides a robust confirmation of momentum strength and trend direction, while ATR ensures dynamic risk management that adapts to volatility. This eliminates overfitting from additional indicators and improves signal quality by focusing on momentum convergence and divergence.",
      "change_type": "logic",
      "diagnostic_category": "ruined",
      "error": null,
      "decision": "continue",
      "sharpe": 0.8080259558588733,
      "return_pct": -2759.74168394525,
      "trades": 2559,
      "score_card": {
        "profitability": {
          "grade": "F",
          "detail": "Return -2759.7%, PF 0.72, Expectancy 0.00"
        },
        "risk": {
          "grade": "F",
          "detail": "MaxDD 100.0%, Vol 0.0%"
        },
        "efficiency": {
          "grade": "C",
          "detail": "Sharpe 0.808, Sortino 0.000, Calmar 0.000"
        },
        "signal_quality": {
          "grade": "D",
          "detail": "WR 29.2%, Trades 2559, AvgW/L 0.00/0.00"
        }
      },
      "phase_feedback": {
        "proposal": {
          "phase": "proposal",
          "initial_kind": "json",
          "realign_attempts": 0,
          "realign_success": false,
          "issues": [],
          "final_kind": "json",
          "final_valid": true
        },
        "code": {
          "phase": "code",
          "initial_kind": "python",
          "realign_attempts": 0,
          "realign_success": false,
          "final_kind": "python",
          "final_valid": true,
          "validation_error": "Usage invalide: `stochastic['k']` pour indicateur dict 'stochastic'. Sous-cl\u00e9s valides: stoch_d, stoch_k.",
          "validation_error_retry": "Usage invalide: indicators['stochastic']['k'] \u2014 sous-cl\u00e9 inconnue. Sous-cl\u00e9s valides: stoch_d, stoch_k.",
          "fallback_deterministic_used": true,
          "source": "deterministic_fallback"
        },
        "decision": {
          "stop_overridden": true
        }
      }
    },
    {
      "iteration": 10,
      "hypothesis": "The current strategy fails because it uses RSI and Bollinger Bands as entry filters, which are prone to whipsaws in trending markets like BTCUSDC. By switching to MACD + STOCHASTIC + ATR as the core combination, we can better capture momentum acceleration and alignment while maintaining robust risk controls. MACD acceleration signals when momentum is increasing, STOCHASTIC alignment confirms trend direction, and ATR-based stops ensure proper risk management.",
      "change_type": "logic",
      "diagnostic_category": "ruined",
      "error": null,
      "decision": "stop",
      "sharpe": 0.8080259558588733,
      "return_pct": -2759.74168394525,
      "trades": 2559,
      "score_card": {
        "profitability": {
          "grade": "F",
          "detail": "Return -2759.7%, PF 0.72, Expectancy 0.00"
        },
        "risk": {
          "grade": "F",
          "detail": "MaxDD 100.0%, Vol 0.0%"
        },
        "efficiency": {
          "grade": "C",
          "detail": "Sharpe 0.808, Sortino 0.000, Calmar 0.000"
        },
        "signal_quality": {
          "grade": "D",
          "detail": "WR 29.2%, Trades 2559, AvgW/L 0.00/0.00"
        }
      },
      "phase_feedback": {
        "proposal": {
          "phase": "proposal",
          "initial_kind": "json",
          "realign_attempts": 0,
          "realign_success": false,
          "issues": [],
          "final_kind": "json",
          "final_valid": true
        },
        "code": {
          "phase": "code",
          "initial_kind": "python",
          "realign_attempts": 0,
          "realign_success": false,
          "final_kind": "python",
          "final_valid": true,
          "validation_error": "Usage invalide: `stochastic['k']` pour indicateur dict 'stochastic'. Sous-cl\u00e9s valides: stoch_d, stoch_k.",
          "validation_error_retry": "Usage invalide: indicators['stochastic']['k'] \u2014 sous-cl\u00e9 inconnue. Sous-cl\u00e9s valides: stoch_d, stoch_k.",
          "fallback_deterministic_used": true,
          "source": "deterministic_fallback"
        }
      }
    }
  ]
}