{
  "run_id": "bollinger_best_longe_3i_LINKUSDC_1h_20260210_143800_c6726c2f",
  "timestamp": "2026-02-10T14:38:00.184389",
  "strategy": "Bollinger_best_longe_3i",
  "symbol": "LINKUSDC",
  "timeframe": "1h",
  "params": {
    "initial_capital": 10000,
    "fees_bps": 10,
    "slippage_bps": 5,
    "bb_period": 20,
    "bb_std": 2.1,
    "entry_level": 0.0,
    "sl_level": -0.5,
    "tp_level": 0.85,
    "leverage": 1.0
  },
  "metrics": {
    "total_pnl": -3230.3589761112144,
    "total_return_pct": -32.30358976111214,
    "sharpe_ratio": 0.38229232037013433,
    "max_drawdown_pct": -79.39252304945087,
    "total_trades": 74,
    "win_rate_pct": 10.81081081081081,
    "profit_factor": 0.7251233035109614,
    "data_coverage_pct": 100.0
  },
  "n_bars": 15672,
  "n_trades": 74,
  "period_start": "2024-04-18 00:00:00+00:00",
  "period_end": "2026-01-30 23:00:00+00:00",
  "duration_sec": 0.004370799999378505
}